tyk_calculator_mcp_server/__init__.py
tyk_calculator_mcp_server/tyk_calculator_mcp_server.py
tyk_calculator_mcp_server-0.1.2.dist-info/licenses/LICENSE
tyk_calculator_mcp_server-0.1.2.dist-info/METADATA
tyk_calculator_mcp_server-0.1.2.dist-info/WHEEL
tyk_calculator_mcp_server-0.1.2.dist-info/entry_points.txt
tyk_calculator_mcp_server-0.1.2.dist-info/top_level.txt
tyk_calculator_mcp_server-0.1.2.dist-info/RECORD
