Metadata-Version: 2.4
Name: tyk-calculator-mcp-server
Version: 0.1.2
Summary: 一个基于MCP协议的计算器服务器
Author-email: tangyongkang <316674908@qq.com>
License: MIT License
Keywords: mcp,calculator,server,llm
Classifier: Development Status :: 3 - Alpha
Classifier: Intended Audience :: Developers
Classifier: License :: OSI Approved :: MIT License
Classifier: Programming Language :: Python :: 3
Classifier: Programming Language :: Python :: 3.8
Classifier: Programming Language :: Python :: 3.9
Classifier: Programming Language :: Python :: 3.10
Classifier: Programming Language :: Python :: 3.11
Requires-Python: >=3.8
License-File: LICENSE
Requires-Dist: mcp; python_version >= "3.8"
Dynamic: license-file
